{
  "last_updated": "14 June 2026 à 10:19 UTC",
  "articles": [
    {
      "source": "Physics Today",
      "title": "Quantum tunneling on water. I. General framework for microdroplet redox chemistry",
      "link": "https://pubs.aip.org/aip/jcp/article/164/22/224709/3394728/Quantum-tunneling-on-water-I-General-framework-for",
      "date": "12 Jun 2026"
    },
    {
      "source": "Physics Today",
      "title": "Quantum tunneling on water. II. Quantitative rate formalism of barrierless electron transfer and application to oxidation reactions",
      "link": "https://pubs.aip.org/aip/jcp/article/164/22/224710/3394645/Quantum-tunneling-on-water-II-Quantitative-rate",
      "date": "12 Jun 2026"
    },
    {
      "source": "Physics Today",
      "title": "Mechanisms for light emission enhancement from low lying doublet states in copper porphyrin  H -aggregates",
      "link": "https://pubs.aip.org/aip/jcp/article/164/22/224312/3394523/Mechanisms-for-light-emission-enhancement-from-low",
      "date": "12 Jun 2026"
    },
    {
      "source": "Physics Today",
      "title": "Decoherence-induced adaptive multiconfigurational Ehrenfest dynamics for nonadiabatic scattering simulations",
      "link": "https://pubs.aip.org/aip/jcp/article/164/22/224128/3394522/Decoherence-induced-adaptive-multiconfigurational",
      "date": "12 Jun 2026"
    },
    {
      "source": "Physics Today",
      "title": "Relativistic strengthening of hydrogen bonds in bihalide anions: A four-component CCSD(T) study",
      "link": "https://pubs.aip.org/aip/jcp/article/164/22/224123/3394469/Relativistic-strengthening-of-hydrogen-bonds-in",
      "date": "11 Jun 2026"
    }
  ]
}