{
  "last_updated": "11 May 2026 à 10:29 UTC",
  "articles": [
    {
      "source": "Nature – Quantum Information",
      "title": "Stabilizer entanglement enhances magic injection",
      "link": "https://www.nature.com/articles/s41534-026-01265-4",
      "date": "11 May 2026"
    },
    {
      "source": "Nature – Quantum Information",
      "title": "Polynomially efficient quantum enabled variational Monte Carlo for training neural-network quantum states for physico-chemical applications",
      "link": "https://www.nature.com/articles/s41534-026-01230-1",
      "date": "08 May 2026"
    },
    {
      "source": "Nature – Quantum Information",
      "title": "Non-Markovianity and memory enhancement in quantum reservoir computing",
      "link": "https://www.nature.com/articles/s41534-026-01257-4",
      "date": "08 May 2026"
    },
    {
      "source": "Nature – Quantum Information",
      "title": "Efficient simulation of low-entanglement bosonic Gaussian states in polynomial time",
      "link": "https://www.nature.com/articles/s41534-026-01254-7",
      "date": "07 May 2026"
    },
    {
      "source": "Nature – Quantum Information",
      "title": "Quantum bipolar thermoelectricity",
      "link": "https://www.nature.com/articles/s41534-026-01237-8",
      "date": "06 May 2026"
    },
    {
      "source": "Physics Today",
      "title": "A missing oxidation node in chlorine–sulfur chemical networks: Accurate spectroscopic signatures of Cl 2 S 2 O isomers",
      "link": "https://pubs.aip.org/aip/jcp/article/164/18/184302/3389290/A-missing-oxidation-node-in-chlorine-sulfur",
      "date": "08 May 2026"
    },
    {
      "source": "Hacker News – Quantum",
      "title": "Ask HN: Is quantum computing worth the struggle?",
      "link": "https://news.ycombinator.com/item?id=48033532",
      "date": "06 May 2026"
    },
    {
      "source": "Hacker News – Quantum",
      "title": "Coinbase Advisers Warn Quantum Computing Will Crack Blockchain Encryption",
      "link": "https://thequantuminsider.com/2026/04/25/coinbase-advisers-warn-quantum-computing-will-crack-blockchain-encryption-and-the-window-to-prepare-is-narrowing/",
      "date": "05 May 2026"
    }
  ]
}